skinfer/__init__.py
skinfer/draft4_generator.py
skinfer/json_schema_merger.py
skinfer/schema_inferer.py
skinfer-0.2.0.data/scripts/json_validator
skinfer-0.2.0.data/scripts/schema_merger
skinfer-0.2.0.data/scripts/skinfer
skinfer-0.2.0.dist-info/DESCRIPTION.rst
skinfer-0.2.0.dist-info/METADATA
skinfer-0.2.0.dist-info/RECORD
skinfer-0.2.0.dist-info/WHEEL
skinfer-0.2.0.dist-info/metadata.json
skinfer-0.2.0.dist-info/top_level.txt
