Metadata-Version: 1.1
Name: skinfer
Version: 0.2.0
Summary: Simple tool to merge JSON schemas
Home-page: https://github.com/scrapinghub/skinfer
Author: Scrapinghub
Author-email: info@scrapinghub.com
License: BSD
Keywords: skinfer json-schema json schema inferer merger
Platform: UNKNOWN
Classifier: Development Status :: 2 - Pre-Alpha
Classifier: Intended Audience :: Developers
Classifier: License :: OSI Approved :: BSD License
Classifier: Natural Language :: English
Classifier: Programming Language :: Python :: 2
Classifier: Programming Language :: Python :: 2.7
Classifier: Programming Language :: Python :: 3
Classifier: Programming Language :: Python :: 3.3
Classifier: Programming Language :: Python :: 3.4
